smawe_pyppeteer/__init__.py
smawe_pyppeteer/__version__.py
smawe_pyppeteer/utils/__init__.py
smawe_pyppeteer/utils/pretend.py
smawe_pyppeteer/utils/smawe_pyppeteer.py
smawe_pyppeteer-0.1.0.dist-info/METADATA
smawe_pyppeteer-0.1.0.dist-info/WHEEL
smawe_pyppeteer-0.1.0.dist-info/top_level.txt
smawe_pyppeteer-0.1.0.dist-info/RECORD
