Metadata-Version: 2.1
Name: smawe-pyppeteer
Version: 0.1.0
Summary: 一个使用pyppeteer进行渲染的请求库
Home-page: https://github.com/Smawexi/SmawePyppeteer
Author: Smawe
Author-email: 1281722462@qq.com
Classifier: Programming Language :: Python :: 3.6
Classifier: Programming Language :: Python :: 3.7
Classifier: Programming Language :: Python :: 3.8
Classifier: Programming Language :: Python :: 3.9
Classifier: Programming Language :: Python :: 3.10
Classifier: Programming Language :: Python :: Implementation :: CPython
Requires-Python: >=3.6.0
Requires-Dist: pyppeteer
